{
    "name": "333",
    "version": "0.0.1",
    "description": "",
    "dependencies": {
        "core": "*",
        "microphone": "*",
        "audio-recording": "*",
        "my-controller": "github:aorczyk/my-controller#v2.2.3",
        "pxt-DS3231": "github:keble6/pxt-ds3231#v1.0.2",
        "MaqueenPlus": "github:dfrobot/pxt-dfrobot-maqueenplus#v1.5.1"
    },
    "files": [
        "main.blocks",
        "main.ts",
        "README.md"
    ],
    "testFiles": [
        "test.ts"
    ],
    "targetVersions": {
        "target": "8.0.22",
        "targetId": "microbit"
    },
    "supportedTargets": [
        "microbit"
    ],
    "preferredEditor": "blocksprj"
}
